dukpy-0.5.0.dist-info/top_level.txt
dukpy-0.5.0.dist-info/RECORD
dukpy-0.5.0.dist-info/LICENSE
dukpy-0.5.0.dist-info/entry_points.txt
dukpy-0.5.0.dist-info/METADATA
dukpy-0.5.0.dist-info/WHEEL
dukpy/babel.py
dukpy/coffee.py
dukpy/lessc.py
dukpy/tsc.py
dukpy/run.py
dukpy/_dukpy.cpython-39-aarch64-linux-gnu.so
dukpy/nodelike.py
dukpy/__init__.py
dukpy/module_loader.py
dukpy/evaljs.py
dukpy/install.py
dukpy/jsmodules/coffeescript.js
dukpy/jsmodules/typescriptServices.js
dukpy/jsmodules/babel-6.26.0.min.js
dukpy/jsmodules/semver.js
dukpy/jsmodules/less/less/index.js
dukpy/jsmodules/less/less/plugin-manager.js
dukpy/jsmodules/less/less/utils.js
dukpy/jsmodules/less/less/parse.js
dukpy/jsmodules/less/less/import-manager.js
dukpy/jsmodules/less/less/render.js
dukpy/jsmodules/less/less/source-map-output.js
dukpy/jsmodules/less/less/contexts.js
dukpy/jsmodules/less/less/logger.js
dukpy/jsmodules/less/less/parse-tree.js
dukpy/jsmodules/less/less/source-map-builder.js
dukpy/jsmodules/less/less/less-error.js
dukpy/jsmodules/less/less/transform-tree.js
dukpy/jsmodules/less/less/data/index.js
dukpy/jsmodules/less/less/data/unit-conversions.js
dukpy/jsmodules/less/less/data/colors.js
dukpy/jsmodules/less/less/visitors/set-tree-visibility-visitor.js
dukpy/jsmodules/less/less/visitors/index.js
dukpy/jsmodules/less/less/visitors/to-css-visitor.js
dukpy/jsmodules/less/less/visitors/import-sequencer.js
dukpy/jsmodules/less/less/visitors/join-selector-visitor.js
dukpy/jsmodules/less/less/visitors/visitor.js
dukpy/jsmodules/less/less/visitors/extend-visitor.js
dukpy/jsmodules/less/less/visitors/import-visitor.js
dukpy/jsmodules/less/less/environment/file-manager-api.js
dukpy/jsmodules/less/less/environment/environment.js
dukpy/jsmodules/less/less/environment/environment-api.js
dukpy/jsmodules/less/less/environment/abstract-file-manager.js
dukpy/jsmodules/less/less/functions/svg.js
dukpy/jsmodules/less/less/functions/index.js
dukpy/jsmodules/less/less/functions/number.js
dukpy/jsmodules/less/less/functions/data-uri.js
dukpy/jsmodules/less/less/functions/function-caller.js
dukpy/jsmodules/less/less/functions/math.js
